apb_spatial_utils/__init__.py
apb_spatial_utils/shapely_utils.py
apb_spatial_utils/topojson_utils.py
apb_spatial_utils-0.1.2.dist-info/METADATA
apb_spatial_utils-0.1.2.dist-info/WHEEL
apb_spatial_utils-0.1.2.dist-info/top_level.txt
apb_spatial_utils-0.1.2.dist-info/RECORD
